enrichm/__init__.py
enrichm/annotate.py
enrichm/classifier.py
enrichm/comparer.py
enrichm/connect.py
enrichm/data.py
enrichm/databases.py
enrichm/draw_plots.py
enrichm/enrichment.py
enrichm/generate.py
enrichm/genome.py
enrichm/gff_generator.py
enrichm/kegg_matrix.py
enrichm/kegg_module_grabber.py
enrichm/matrix_generator.py
enrichm/metagenome_analyzer.py
enrichm/module_description_parser.py
enrichm/network_analyzer.py
enrichm/network_builder.py
enrichm/parse_annotate.py
enrichm/parser.py
enrichm/predict.py
enrichm/run.py
enrichm/sequence_io.py
enrichm/traverse.py
enrichm/version.py
enrichm-0.4.3.data/scripts/enrichm
enrichm-0.4.3.dist-info/METADATA
enrichm-0.4.3.dist-info/RECORD
enrichm-0.4.3.dist-info/WHEEL
enrichm-0.4.3.dist-info/top_level.txt
