Metadata-Version: 2.1
Name: enrichm
Version: 0.4.3
Summary: enrichm is a toolbox for comparing the functional composition of population genomes
Home-page: https://github.com/geronimp/enrichM
Author: Joel Boyd, Ben Woodcroft, Alexander Baker
Author-email: joel.boyd@uqconnect.edu.au
License: GPL3+
Download-URL: https://github.com/geronimp/enrichm/archive/0.4.3.tar.gz
Keywords: MAGs,Population genomes,metagenomics,Annotation,Comparison
Platform: UNKNOWN
Requires-Dist: python-dateutil (>=2.5.1)
Requires-Dist: statsmodels (>=0.8.0rc1)
Requires-Dist: numpy (>=1.9.1)
Requires-Dist: pandas (>=0.17.1)
Requires-Dist: scipy (>=0.17.0)
Requires-Dist: biopython (>=1.66)
Requires-Dist: six (>=1.10.0)
Requires-Dist: sklearn (>=0.0)
